{
  "title": "One Piece",
  "description": "",
  "artist": "Eiichirō Oda",
  "author": "Eiichirō Oda",
  "cover": "https://imgchest.com/p/n87wnljvb7x",
  "chapters": {
    "1114": {
      "title": "1114",
      "volume": "",
      "last_updated": "1765220806",
      "groups": {
        "": [
          "https://cdn.imgchest.com/files/6b430955cde6.jpg",
          "https://cdn.imgchest.com/files/57245b24d7d7.jpg",
          "https://cdn.imgchest.com/files/f9237eb26c05.jpg",
          "https://cdn.imgchest.com/files/bdbbf499e878.jpg",
          "https://cdn.imgchest.com/files/68a0d758a566.jpg",
          "https://cdn.imgchest.com/files/92b899cabbce.jpg",
          "https://cdn.imgchest.com/files/29e51aecf6bc.jpg",
          "https://cdn.imgchest.com/files/ee4584ec4760.jpg",
          "https://cdn.imgchest.com/files/671f4d9c9684.jpg",
          "https://cdn.imgchest.com/files/c433aa36b904.jpg",
          "https://cdn.imgchest.com/files/233e13a39076.jpg",
          "https://cdn.imgchest.com/files/15316ba7e281.jpg",
          "https://cdn.imgchest.com/files/a238dc95e37c.jpg"
        ]
      }
    },
    "1115": {
      "title": "1115",
      "volume": "",
      "last_updated": "1765244278",
      "groups": {
        "": [
          "https://cdn.imgchest.com/files/f421f483fce6.jpg",
          "https://cdn.imgchest.com/files/70e025a1e750.jpg",
          "https://cdn.imgchest.com/files/b80cafda1d5a.jpg",
          "https://cdn.imgchest.com/files/44059307a3bc.jpg",
          "https://cdn.imgchest.com/files/ba07f692c81c.jpg",
          "https://cdn.imgchest.com/files/86e3a3a60fc0.jpg",
          "https://cdn.imgchest.com/files/68c028f57766.jpg",
          "https://cdn.imgchest.com/files/52becacbc18d.jpg",
          "https://cdn.imgchest.com/files/c7ffc3f384c8.jpg",
          "https://cdn.imgchest.com/files/ad46df89b0c4.jpg",
          "https://cdn.imgchest.com/files/d0de9aff3fee.jpg",
          "https://cdn.imgchest.com/files/e9b869c1c345.jpg",
          "https://cdn.imgchest.com/files/e0da6be16e54.jpg",
          "https://cdn.imgchest.com/files/94f0a15a2b1a.jpg",
          "https://cdn.imgchest.com/files/9797a69531ed.jpg"
        ]
      }
    },
    "1116": {
      "title": "1116",
      "volume": "",
      "last_updated": "1765250389",
      "groups": {
        "": [
          "https://cdn.imgchest.com/files/dd9b5a3b70fe.jpg",
          "https://cdn.imgchest.com/files/935c58d1eb0b.jpg",
          "https://cdn.imgchest.com/files/8ee767059fa3.jpg",
          "https://cdn.imgchest.com/files/9f72a42670f1.jpg",
          "https://cdn.imgchest.com/files/7c339790985c.jpg",
          "https://cdn.imgchest.com/files/9e7b716afee3.jpg",
          "https://cdn.imgchest.com/files/5ec79e23893d.jpg",
          "https://cdn.imgchest.com/files/e084194599b3.jpg",
          "https://cdn.imgchest.com/files/178ac4b6fc42.jpg",
          "https://cdn.imgchest.com/files/5fa6cb3327d2.jpg",
          "https://cdn.imgchest.com/files/28c412e553e5.jpg",
          "https://cdn.imgchest.com/files/1a902043ef72.jpg"
        ]
      }
    },
    "1117": {
      "title": "1117",
      "volume": "",
      "last_updated": "1765250435",
      "groups": {
        "": [
          "https://cdn.imgchest.com/files/938628f54440.jpg",
          "https://cdn.imgchest.com/files/e7f6c38919fc.jpg",
          "https://cdn.imgchest.com/files/8b6747775e5e.jpg",
          "https://cdn.imgchest.com/files/5ab815fbd677.jpg",
          "https://cdn.imgchest.com/files/2ff65acbb9a5.jpg",
          "https://cdn.imgchest.com/files/d3afeeb083e4.jpg",
          "https://cdn.imgchest.com/files/bcaafee35f8a.jpg",
          "https://cdn.imgchest.com/files/559c0f39d7e0.jpg",
          "https://cdn.imgchest.com/files/332080fe70c2.jpg",
          "https://cdn.imgchest.com/files/149cb8155684.jpg",
          "https://cdn.imgchest.com/files/aa1b0eb1e7f2.jpg",
          "https://cdn.imgchest.com/files/6d593f1a05b3.jpg",
          "https://cdn.imgchest.com/files/a23ba09bcdd3.jpg",
          "https://cdn.imgchest.com/files/f0978f073fb1.jpg",
          "https://cdn.imgchest.com/files/58158ce12df3.jpg",
          "https://cdn.imgchest.com/files/b51d9f6c1c73.jpg",
          "https://cdn.imgchest.com/files/1f09c730e9e5.jpg"
        ]
      }
    },
    "1118": {
      "title": "1118",
      "volume": "",
      "last_updated": "1765250460",
      "groups": {
        "": [
          "https://cdn.imgchest.com/files/7b917b47f453.jpg",
          "https://cdn.imgchest.com/files/dc473b30b52e.jpg",
          "https://cdn.imgchest.com/files/598309b83332.jpg",
          "https://cdn.imgchest.com/files/96d6b8d93e2c.jpg",
          "https://cdn.imgchest.com/files/0f4b61fddd44.jpg",
          "https://cdn.imgchest.com/files/3e2ff23cc022.jpg",
          "https://cdn.imgchest.com/files/a51d3026fd6c.jpg",
          "https://cdn.imgchest.com/files/c81ec3bbdd51.jpg",
          "https://cdn.imgchest.com/files/989236e9a7a7.jpg",
          "https://cdn.imgchest.com/files/e4ce8e077b16.jpg",
          "https://cdn.imgchest.com/files/abe725676cf6.jpg",
          "https://cdn.imgchest.com/files/e0aefaeb7506.jpg",
          "https://cdn.imgchest.com/files/df1459fc94ce.jpg"
        ]
      }
    },
    "1119": {
      "title": "1119",
      "volume": "",
      "last_updated": "1765250504",
      "groups": {
        "": [
          "https://cdn.imgchest.com/files/9a4de3aea918.jpg",
          "https://cdn.imgchest.com/files/dede9de8d4d4.jpg",
          "https://cdn.imgchest.com/files/94e175c5e76a.jpg",
          "https://cdn.imgchest.com/files/901b9e4ba45d.jpg",
          "https://cdn.imgchest.com/files/bb0b03fac17b.jpg",
          "https://cdn.imgchest.com/files/e15191a56a66.jpg",
          "https://cdn.imgchest.com/files/582b5a4dfaa2.jpg",
          "https://cdn.imgchest.com/files/83fbe2469de4.jpg",
          "https://cdn.imgchest.com/files/68a09beb35fa.jpg",
          "https://cdn.imgchest.com/files/bcc2c72ebd9b.jpg",
          "https://cdn.imgchest.com/files/ff4aec442c52.jpg",
          "https://cdn.imgchest.com/files/6aba41a12dc2.jpg",
          "https://cdn.imgchest.com/files/109002be9a22.jpg"
        ]
      }
    },
    "1120": {
      "title": "1120",
      "volume": "",
      "last_updated": "1765250516",
      "groups": {
        "": [
          "https://cdn.imgchest.com/files/80e6dc52f353.jpg",
          "https://cdn.imgchest.com/files/247c1e64d9bd.jpg",
          "https://cdn.imgchest.com/files/6b152800bbbd.jpg",
          "https://cdn.imgchest.com/files/d64803aa6c15.jpg",
          "https://cdn.imgchest.com/files/865d0a8426b6.jpg",
          "https://cdn.imgchest.com/files/b70f4a396178.jpg",
          "https://cdn.imgchest.com/files/7e472e4bf71c.jpg",
          "https://cdn.imgchest.com/files/ca6cbd211539.jpg",
          "https://cdn.imgchest.com/files/7bc8f1dc91c4.jpg",
          "https://cdn.imgchest.com/files/7b2922bb3dc7.jpg",
          "https://cdn.imgchest.com/files/72ed1ecd7a1c.jpg",
          "https://cdn.imgchest.com/files/daeea18dc04e.jpg",
          "https://cdn.imgchest.com/files/18fe62b8f6e6.jpg",
          "https://cdn.imgchest.com/files/d8ce0ca288d5.jpg",
          "https://cdn.imgchest.com/files/19d6e59a0391.jpg",
          "https://cdn.imgchest.com/files/37d097738a24.jpg",
          "https://cdn.imgchest.com/files/b9c9ad998143.jpg",
          "https://cdn.imgchest.com/files/b1fdf84bc395.jpg",
          "https://cdn.imgchest.com/files/85af3e79c9ea.jpg"
        ]
      }
    },
    "1121": {
      "title": "1121",
      "volume": "",
      "last_updated": "1765251215",
      "groups": {
        "": [
          "https://cdn.imgchest.com/files/b6d9332b63f7.jpg",
          "https://cdn.imgchest.com/files/2fc571df09e8.jpg",
          "https://cdn.imgchest.com/files/d36164332536.jpg",
          "https://cdn.imgchest.com/files/0d55a4a91a0c.jpg",
          "https://cdn.imgchest.com/files/0f317b68bd33.jpg",
          "https://cdn.imgchest.com/files/1144b4d64723.jpg",
          "https://cdn.imgchest.com/files/6d12098742b1.jpg",
          "https://cdn.imgchest.com/files/bcbeb661fa0b.jpg",
          "https://cdn.imgchest.com/files/b121142241d1.jpg",
          "https://cdn.imgchest.com/files/707f2127f7db.jpg",
          "https://cdn.imgchest.com/files/10974bff986e.jpg",
          "https://cdn.imgchest.com/files/7608c3309163.jpg",
          "https://cdn.imgchest.com/files/71871d307c0b.jpg",
          "https://cdn.imgchest.com/files/69e840e59e45.jpg",
          "https://cdn.imgchest.com/files/b59250552d45.jpg",
          "https://cdn.imgchest.com/files/dd64bcecd806.jpg",
          "https://cdn.imgchest.com/files/aaedb3a514f5.jpg",
          "https://cdn.imgchest.com/files/001fed0cfe07.jpg"
        ]
      }
    },
    "1122": {
      "title": "1122",
      "volume": "",
      "last_updated": "1765251231",
      "groups": {
        "": [
          "https://cdn.imgchest.com/files/c015561cb6f8.jpg",
          "https://cdn.imgchest.com/files/7dd2b7ee8970.jpg",
          "https://cdn.imgchest.com/files/8fea636db653.jpg",
          "https://cdn.imgchest.com/files/d7d75f51be65.jpg",
          "https://cdn.imgchest.com/files/93f1fea78c46.jpg",
          "https://cdn.imgchest.com/files/40f0f3c82672.jpg",
          "https://cdn.imgchest.com/files/b7173109136e.jpg",
          "https://cdn.imgchest.com/files/9f98b794ad97.jpg",
          "https://cdn.imgchest.com/files/319a957f2c6b.jpg",
          "https://cdn.imgchest.com/files/b93a9fdcef23.jpg",
          "https://cdn.imgchest.com/files/10268ed68a10.jpg",
          "https://cdn.imgchest.com/files/251672654050.jpg",
          "https://cdn.imgchest.com/files/03f9c9a6ee35.jpg"
        ]
      }
    },
    "1123": {
      "title": "1123",
      "volume": "",
      "last_updated": "1765251272",
      "groups": {
        "": [
          "https://cdn.imgchest.com/files/a95fff764d27.jpg",
          "https://cdn.imgchest.com/files/eb0a85d50f07.jpg",
          "https://cdn.imgchest.com/files/3473657881b1.jpg",
          "https://cdn.imgchest.com/files/b1044e41f4e2.jpg",
          "https://cdn.imgchest.com/files/a3657360571c.jpg",
          "https://cdn.imgchest.com/files/60ab22dceea5.jpg",
          "https://cdn.imgchest.com/files/7ec89822cd46.jpg",
          "https://cdn.imgchest.com/files/c66e22ca7a69.jpg",
          "https://cdn.imgchest.com/files/38ab225e2c77.jpg",
          "https://cdn.imgchest.com/files/414b147658fd.jpg",
          "https://cdn.imgchest.com/files/dff3dc273312.jpg",
          "https://cdn.imgchest.com/files/2bd755de6f8d.jpg",
          "https://cdn.imgchest.com/files/78b778eed046.jpg",
          "https://cdn.imgchest.com/files/8c992d6b9060.jpg",
          "https://cdn.imgchest.com/files/88a0a6778f3e.jpg",
          "https://cdn.imgchest.com/files/506d6db4fd97.jpg",
          "https://cdn.imgchest.com/files/55cfd4fbd959.jpg",
          "https://cdn.imgchest.com/files/2b2c4781fb63.jpg",
          "https://cdn.imgchest.com/files/9f6746fbb401.jpg",
          "https://cdn.imgchest.com/files/680025f139a2.jpg",
          "https://cdn.imgchest.com/files/f98b0138f6fc.jpg",
          "https://cdn.imgchest.com/files/bc08afb1a5b2.jpg",
          "https://cdn.imgchest.com/files/96c1d6b8cce0.jpg",
          "https://cdn.imgchest.com/files/48dfe63338ca.jpg",
          "https://cdn.imgchest.com/files/aba6a703a224.jpg",
          "https://cdn.imgchest.com/files/bcd4306cd93d.jpg",
          "https://cdn.imgchest.com/files/091cb3198356.jpg",
          "https://cdn.imgchest.com/files/cf027c08fe9c.jpg",
          "https://cdn.imgchest.com/files/a4d229e1b419.jpg",
          "https://cdn.imgchest.com/files/e755f4657012.jpg"
        ]
      }
    },
    "1124": {
      "title": "1124",
      "volume": "",
      "last_updated": "1765251291",
      "groups": {
        "": [
          "https://cdn.imgchest.com/files/4516340fa2a4.jpg",
          "https://cdn.imgchest.com/files/145331d56abd.jpg",
          "https://cdn.imgchest.com/files/1406a116569d.jpg",
          "https://cdn.imgchest.com/files/e845e39cb83c.jpg",
          "https://cdn.imgchest.com/files/9c32d0d2f28d.jpg",
          "https://cdn.imgchest.com/files/7fa778f8a73d.jpg",
          "https://cdn.imgchest.com/files/7e3c2934dc6e.jpg",
          "https://cdn.imgchest.com/files/669b5b82804c.jpg",
          "https://cdn.imgchest.com/files/7c6dd66a267b.jpg",
          "https://cdn.imgchest.com/files/354874a27211.jpg",
          "https://cdn.imgchest.com/files/811a5e1cdc0e.jpg"
        ]
      }
    },
    "1125": {
      "title": "1125",
      "volume": "",
      "last_updated": "1765251307",
      "groups": {
        "": [
          "https://cdn.imgchest.com/files/50f774619960.jpg",
          "https://cdn.imgchest.com/files/65f96a305e46.jpg",
          "https://cdn.imgchest.com/files/89a075f15f2c.jpg",
          "https://cdn.imgchest.com/files/b350b3ca4f35.jpg",
          "https://cdn.imgchest.com/files/d09cf67281eb.jpg",
          "https://cdn.imgchest.com/files/f884f715d2c4.jpg",
          "https://cdn.imgchest.com/files/4ace98115835.jpg",
          "https://cdn.imgchest.com/files/3abb0d36095b.jpg",
          "https://cdn.imgchest.com/files/bdc0a6f99936.jpg",
          "https://cdn.imgchest.com/files/8d4379a53678.jpg",
          "https://cdn.imgchest.com/files/15f5bcdda971.jpg",
          "https://cdn.imgchest.com/files/1c55efb400a4.jpg",
          "https://cdn.imgchest.com/files/b5d770ace1ed.jpg",
          "https://cdn.imgchest.com/files/da898c9585df.jpg",
          "https://cdn.imgchest.com/files/d14b745b3ad7.jpg",
          "https://cdn.imgchest.com/files/d3c48593b376.jpg",
          "https://cdn.imgchest.com/files/3b644c532ab4.jpg"
        ]
      }
    },
    "1126": {
      "title": "1126",
      "volume": "",
      "last_updated": "1765251353",
      "groups": {
        "": [
          "https://cdn.imgchest.com/files/dd6632b88690.jpg",
          "https://cdn.imgchest.com/files/60c9cf8af88f.jpg",
          "https://cdn.imgchest.com/files/e13e95ee58af.jpg",
          "https://cdn.imgchest.com/files/5d2eb0960047.jpg",
          "https://cdn.imgchest.com/files/21570a948e80.jpg",
          "https://cdn.imgchest.com/files/1f0c5179d016.jpg",
          "https://cdn.imgchest.com/files/66e605d80c45.jpg",
          "https://cdn.imgchest.com/files/c5ba991642c5.jpg",
          "https://cdn.imgchest.com/files/ff151029b64d.jpg",
          "https://cdn.imgchest.com/files/88b9fecca9ea.jpg",
          "https://cdn.imgchest.com/files/712418557956.jpg",
          "https://cdn.imgchest.com/files/4e34987dac75.jpg",
          "https://cdn.imgchest.com/files/7fc2e112f84b.jpg",
          "https://cdn.imgchest.com/files/7062f918425f.jpg",
          "https://cdn.imgchest.com/files/62908b9701a8.jpg"
        ]
      }
    },
    "1127": {
      "title": "1127",
      "volume": "",
      "last_updated": "1765251371",
      "groups": {
        "": [
          "https://cdn.imgchest.com/files/386974955cfd.jpg",
          "https://cdn.imgchest.com/files/d5957a27ede5.jpg",
          "https://cdn.imgchest.com/files/e48be89d0095.jpg",
          "https://cdn.imgchest.com/files/2cf79fd88ce2.jpg",
          "https://cdn.imgchest.com/files/3eab5da29f07.jpg",
          "https://cdn.imgchest.com/files/de3d1624307f.jpg",
          "https://cdn.imgchest.com/files/b39f240166e2.jpg",
          "https://cdn.imgchest.com/files/90896adcbc2c.jpg",
          "https://cdn.imgchest.com/files/ef40dcb4cd0a.jpg",
          "https://cdn.imgchest.com/files/eb253a3e6844.jpg",
          "https://cdn.imgchest.com/files/3fac1e72132c.jpg",
          "https://cdn.imgchest.com/files/8cb936289b62.jpg",
          "https://cdn.imgchest.com/files/f4f76c9e2e9a.jpg",
          "https://cdn.imgchest.com/files/6e526d1d701b.jpg",
          "https://cdn.imgchest.com/files/b410369269c4.jpg",
          "https://cdn.imgchest.com/files/fcd9f6b29eac.jpg",
          "https://cdn.imgchest.com/files/5d5234ef2e2e.jpg",
          "https://cdn.imgchest.com/files/3c80e9711374.jpg",
          "https://cdn.imgchest.com/files/77b1c59e488b.jpg",
          "https://cdn.imgchest.com/files/0f16620e2fec.jpg",
          "https://cdn.imgchest.com/files/d2c0950a17a8.jpg",
          "https://cdn.imgchest.com/files/e2b9f7a92123.jpg",
          "https://cdn.imgchest.com/files/69a5e3e8600c.jpg",
          "https://cdn.imgchest.com/files/aaca36ba6f3e.jpg",
          "https://cdn.imgchest.com/files/54111d6dfa23.jpg",
          "https://cdn.imgchest.com/files/201844fb3365.jpg",
          "https://cdn.imgchest.com/files/265bf9fc79e7.jpg",
          "https://cdn.imgchest.com/files/8c5e284fcb97.jpg",
          "https://cdn.imgchest.com/files/3431f0a65e4c.jpg"
        ]
      }
    }
  }
}